infosystem/__init__.py
infosystem/_version.py
infosystem/celery.py
infosystem/database.py
infosystem/queue.py
infosystem/request.py
infosystem/resources.py
infosystem/scheduler.py
infosystem/system.py
infosystem/bootstrap/__init__.py
infosystem/bootstrap/roles.py
infosystem/bootstrap/routes.py
infosystem/bootstrap/default/__init__.py
infosystem/bootstrap/default/application.py
infosystem/bootstrap/default/domain.py
infosystem/bootstrap/default/policies.py
infosystem/bootstrap/default/user.py
infosystem/common/__init__.py
infosystem/common/exception.py
infosystem/common/input.py
infosystem/common/operation_after_post.py
infosystem/common/utils.py
infosystem/common/subsystem/__init__.py
infosystem/common/subsystem/apihandler.py
infosystem/common/subsystem/controller.py
infosystem/common/subsystem/driver.py
infosystem/common/subsystem/entity.py
infosystem/common/subsystem/manager.py
infosystem/common/subsystem/operation.py
infosystem/common/subsystem/pagination.py
infosystem/common/subsystem/router.py
infosystem/common/subsystem/transaction_manager.py
infosystem/subsystem/__init__.py
infosystem/subsystem/application/__init__.py
infosystem/subsystem/application/controller.py
infosystem/subsystem/application/manager.py
infosystem/subsystem/application/resource.py
infosystem/subsystem/application/router.py
infosystem/subsystem/capability/__init__.py
infosystem/subsystem/capability/manager.py
infosystem/subsystem/capability/resource.py
infosystem/subsystem/domain/__init__.py
infosystem/subsystem/domain/controller.py
infosystem/subsystem/domain/manager.py
infosystem/subsystem/domain/resource.py
infosystem/subsystem/domain/router.py
infosystem/subsystem/domain/tasks.py
infosystem/subsystem/domain_sequence/__init__.py
infosystem/subsystem/domain_sequence/controller.py
infosystem/subsystem/domain_sequence/driver.py
infosystem/subsystem/domain_sequence/manager.py
infosystem/subsystem/domain_sequence/resource.py
infosystem/subsystem/domain_sequence/router.py
infosystem-1.2.18.dist-info/AUTHORS
infosystem-1.2.18.dist-info/LICENSE
infosystem-1.2.18.dist-info/METADATA
infosystem-1.2.18.dist-info/WHEEL
infosystem-1.2.18.dist-info/top_level.txt
infosystem-1.2.18.dist-info/RECORD
