Metadata-Version: 2.1
Name: infosystem
Version: 1.2.18
Summary: UNKNOWN
Home-page: https://github.com/objetorelacional/infosystem
Author: Samuel de Medeiros Queiroz, Francois Oliveira
Author-email: samueldmq@gmail.com, oliveira.francois@gmail.com
License: Apache-2
Platform: UNKNOWN
License-File: LICENSE
License-File: AUTHORS
Requires-Dist: alembic (==1.6.2)
Requires-Dist: amqp (==5.0.6)
Requires-Dist: APScheduler (==3.7.0)
Requires-Dist: attrs (==21.2.0)
Requires-Dist: billiard (==3.6.4.0)
Requires-Dist: celery (==5.0.5)
Requires-Dist: certifi (==2020.12.5)
Requires-Dist: chardet (==4.0.0)
Requires-Dist: click (==7.1.2)
Requires-Dist: click-didyoumean (==0.0.3)
Requires-Dist: click-plugins (==1.1.1)
Requires-Dist: click-repl (==0.1.6)
Requires-Dist: colorama (==0.4.4)
Requires-Dist: decorator (==5.0.8)
Requires-Dist: Flask (==2.0.0)
Requires-Dist: Flask-Migrate (==2.7.0)
Requires-Dist: Flask-RBAC (==0.5.0)
Requires-Dist: Flask-SQLAlchemy (==2.5.1)
Requires-Dist: gabbi (==2.2.0)
Requires-Dist: greenlet (==1.1.0)
Requires-Dist: idna (==2.10)
Requires-Dist: iniconfig (==1.1.1)
Requires-Dist: itsdangerous (==2.0.0)
Requires-Dist: Jinja2 (==3.0.0)
Requires-Dist: jsonpath-rw (==1.4.0)
Requires-Dist: jsonpath-rw-ext (==1.2.2)
Requires-Dist: kombu (==5.0.2)
Requires-Dist: Mako (==1.1.4)
Requires-Dist: MarkupSafe (==2.0.0)
Requires-Dist: packaging (==20.9)
Requires-Dist: pbr (==5.6.0)
Requires-Dist: pika (==1.2.0)
Requires-Dist: Pillow (==8.4.0)
Requires-Dist: pluggy (==0.13.1)
Requires-Dist: ply (==3.11)
Requires-Dist: prompt-toolkit (==3.0.18)
Requires-Dist: py (==1.10.0)
Requires-Dist: pyparsing (==2.4.7)
Requires-Dist: pytest (==6.2.4)
Requires-Dist: python-dateutil (==2.8.1)
Requires-Dist: python-editor (==1.0.4)
Requires-Dist: pytz (==2021.1)
Requires-Dist: PyYAML (==5.4.1)
Requires-Dist: requests (==2.25.1)
Requires-Dist: six (==1.16.0)
Requires-Dist: sparkpost (==1.3.9)
Requires-Dist: SQLAlchemy (==1.4.15)
Requires-Dist: toml (==0.10.2)
Requires-Dist: tzlocal (==2.1)
Requires-Dist: urllib3 (==1.26.5)
Requires-Dist: vine (==5.0.0)
Requires-Dist: wcwidth (==0.2.5)
Requires-Dist: Werkzeug (==2.0.0)
Requires-Dist: wsgi-intercept (==1.9.2)
